<?xml version="1.0" encoding="utf-8"?>
<TextureAtlas imagePath="rondies.png">
	<!-- Created with Adobe Animate version 20.0.1.19255 -->
	<!-- http://www.adobe.com/products/animate.html -->
	<SubTexture name="ron confirm0000" x="5" y="5" width="471" height="193"/>
	<SubTexture name="ron confirm0001" x="5" y="5" width="471" height="193"/>
	<SubTexture name="ron confirm0002" x="481" y="5" width="471" height="188" frameX="0" frameY="-5" frameWidth="471" frameHeight="193"/>
	<SubTexture name="ron confirm0003" x="481" y="5" width="471" height="188" frameX="0" frameY="-5" frameWidth="471" frameHeight="193"/>
	<SubTexture name="ron confirm0004" x="6419" y="3153" width="471" height="182" frameX="0" frameY="-11" frameWidth="471" frameHeight="183"/>
	<SubTexture name="ron confirm0005" x="6419" y="3153" width="471" height="182" frameX="0" frameY="-11" frameWidth="471" frameHeight="183"/>
	<SubTexture name="ron confirm0006" x="6419" y="3153" width="471" height="182" frameX="0" frameY="-11" frameWidth="471" frameHeight="183"/>
	<SubTexture name="ron confirm0007" x="6419" y="3153" width="471" height="182" frameX="0" frameY="-11" frameWidth="471" frameHeight="183"/>
	<SubTexture name="ron confirm0008" x="6419" y="3153" width="471" height="182" frameX="0" frameY="-11" frameWidth="471" frameHeight="183"/>
	<SubTexture name="ron confirm0009" x="6419" y="3153" width="471" height="182" frameX="0" frameY="-11" frameWidth="471" frameHeight="183"/>
	<SubTexture name="ron confirm0010" x="6419" y="3153" width="471" height="182" frameX="0" frameY="-11" frameWidth="471" frameHeight="183"/>
	<SubTexture name="ron confirm0011" x="6419" y="3153" width="471" height="182" frameX="0" frameY="-11" frameWidth="471" frameHeight="183"/>
	<SubTexture name="ron confirm0012" x="6419" y="3153" width="471" height="182" frameX="0" frameY="-11" frameWidth="471" frameHeight="183"/>
	<SubTexture name="ron confirm0013" x="6419" y="3153" width="471" height="182" frameX="0" frameY="-11" frameWidth="471" frameHeight="183"/>
	<SubTexture name="ron confirm0014" x="6419" y="3153" width="471" height="182" frameX="0" frameY="-11" frameWidth="471" frameHeight="183"/>
	<SubTexture name="ron death0000" x="957" y="5" width="366" height="394" frameX="-1934" frameY="-1273" frameWidth="4371" frameHeight="1734"/>
	<SubTexture name="ron death0001" x="957" y="5" width="366" height="394" frameX="-1934" frameY="-1273" frameWidth="4371" frameHeight="1734"/>
	<SubTexture name="ron death0002" x="1328" y="5" width="368" height="391" frameX="-1933" frameY="-1274" frameWidth="4371" frameHeight="1734"/>
	<SubTexture name="ron death0003" x="1328" y="5" width="368" height="391" frameX="-1933" frameY="-1274" frameWidth="4371" frameHeight="1734"/>
	<SubTexture name="ron death0004" x="1701" y="5" width="368" height="387" frameX="-1933" frameY="-1278" frameWidth="4371" frameHeight="1734"/>
	<SubTexture name="ron death0005" x="2074" y="5" width="368" height="387" frameX="-1933" frameY="-1278" frameWidth="4371" frameHeight="1734"/>
	<SubTexture name="ron death0006" x="2447" y="5" width="368" height="387" frameX="-1933" frameY="-1278" frameWidth="4371" frameHeight="1734"/>
	<SubTexture name="ron death0007" x="2820" y="5" width="368" height="387" frameX="-1933" frameY="-1278" frameWidth="4371" frameHeight="1734"/>
	<SubTexture name="ron death0008" x="2820" y="5" width="368" height="387" frameX="-1933" frameY="-1278" frameWidth="4371" frameHeight="1734"/>
	<SubTexture name="ron death0009" x="2820" y="5" width="368" height="387" frameX="-1933" frameY="-1278" frameWidth="4371" frameHeight="1734"/>
	<SubTexture name="ron death0010" x="3193" y="5" width="368" height="387" frameX="-1933" frameY="-1278" frameWidth="4371" frameHeight="1734"/>
	<SubTexture name="ron death0011" x="3193" y="5" width="368" height="387" frameX="-1933" frameY="-1278" frameWidth="4371" frameHeight="1734"/>
	<SubTexture name="ron death0012" x="3566" y="5" width="367" height="385" frameX="-1934" frameY="-1279" frameWidth="4371" frameHeight="1734"/>
	<SubTexture name="ron death0013" x="3566" y="5" width="367" height="385" frameX="-1934" frameY="-1279" frameWidth="4371" frameHeight="1734"/>
	<SubTexture name="ron death0014" x="3938" y="5" width="377" height="385" frameX="-1940" frameY="-1278" frameWidth="4371" frameHeight="1734"/>
	<SubTexture name="ron death0015" x="3938" y="5" width="377" height="385" frameX="-1940" frameY="-1278" frameWidth="4371" frameHeight="1734"/>
	<SubTexture name="ron death0016" x="4320" y="5" width="377" height="386" frameX="-1941" frameY="-1277" frameWidth="4371" frameHeight="1734"/>
	<SubTexture name="ron death0017" x="4320" y="5" width="377" height="386" frameX="-1941" frameY="-1277" frameWidth="4371" frameHeight="1734"/>
	<SubTexture name="ron death0018" x="4320" y="5" width="377" height="386" frameX="-1941" frameY="-1277" frameWidth="4371" frameHeight="1734"/>
	<SubTexture name="ron death0019" x="4320" y="5" width="377" height="386" frameX="-1941" frameY="-1277" frameWidth="4371" frameHeight="1734"/>
	<SubTexture name="ron death0020" x="4320" y="5" width="377" height="386" frameX="-1941" frameY="-1277" frameWidth="4371" frameHeight="1734"/>
	<SubTexture name="ron death0021" x="4320" y="5" width="377" height="386" frameX="-1941" frameY="-1277" frameWidth="4371" frameHeight="1734"/>
	<SubTexture name="ron death0022" x="4320" y="5" width="377" height="386" frameX="-1941" frameY="-1277" frameWidth="4371" frameHeight="1734"/>
	<SubTexture name="ron death0023" x="4320" y="5" width="377" height="386" frameX="-1941" frameY="-1277" frameWidth="4371" frameHeight="1734"/>
	<SubTexture name="ron death0024" x="4320" y="5" width="377" height="386" frameX="-1941" frameY="-1277" frameWidth="4371" frameHeight="1734"/>
	<SubTexture name="ron death0025" x="4320" y="5" width="377" height="386" frameX="-1941" frameY="-1277" frameWidth="4371" frameHeight="1734"/>
	<SubTexture name="ron death0026" x="4320" y="5" width="377" height="386" frameX="-1941" frameY="-1277" frameWidth="4371" frameHeight="1734"/>
	<SubTexture name="ron death0027" x="4320" y="5" width="377" height="386" frameX="-1941" frameY="-1277" frameWidth="4371" frameHeight="1734"/>
	<SubTexture name="ron death0028" x="4320" y="5" width="377" height="386" frameX="-1941" frameY="-1277" frameWidth="4371" frameHeight="1734"/>
	<SubTexture name="ron death0029" x="4320" y="5" width="377" height="386" frameX="-1941" frameY="-1277" frameWidth="4371" frameHeight="1734"/>
	<SubTexture name="ron death0030" x="4320" y="5" width="377" height="386" frameX="-1941" frameY="-1277" frameWidth="4371" frameHeight="1734"/>
	<SubTexture name="ron death0031" x="4320" y="5" width="377" height="386" frameX="-1941" frameY="-1277" frameWidth="4371" frameHeight="1734"/>
	<SubTexture name="ron death0032" x="4320" y="5" width="377" height="386" frameX="-1941" frameY="-1277" frameWidth="4371" frameHeight="1734"/>
	<SubTexture name="ron death0033" x="4320" y="5" width="377" height="386" frameX="-1941" frameY="-1277" frameWidth="4371" frameHeight="1734"/>
	<SubTexture name="ron death0034" x="4320" y="5" width="377" height="386" frameX="-1941" frameY="-1277" frameWidth="4371" frameHeight="1734"/>
	<SubTexture name="ron death0035" x="4320" y="5" width="377" height="386" frameX="-1941" frameY="-1277" frameWidth="4371" frameHeight="1734"/>
	<SubTexture name="ron death0036" x="4702" y="5" width="2430" height="425" frameX="-1941" frameY="-1277" frameWidth="4371" frameHeight="1734"/>
	<SubTexture name="ron death0037" x="5" y="435" width="1910" height="425" frameX="-1941" frameY="-1277" frameWidth="4371" frameHeight="1734"/>
	<SubTexture name="ron death0038" x="1920" y="435" width="1330" height="425" frameX="-1941" frameY="-1277" frameWidth="4371" frameHeight="1734"/>
	<SubTexture name="ron death0039" x="3255" y="435" width="1025" height="584" frameX="-1871" frameY="-1118" frameWidth="4371" frameHeight="1734"/>
	<SubTexture name="ron death0040" x="4285" y="435" width="1356" height="946" frameX="-1077" frameY="-756" frameWidth="4371" frameHeight="1734"/>
	<SubTexture name="ron death0041" x="5646" y="435" width="1746" height="1243" frameX="-610" frameY="-459" frameWidth="4371" frameHeight="1734"/>
	<SubTexture name="ron death0042" x="5" y="1683" width="2275" height="1465" frameX="0" frameY="-237" frameWidth="4371" frameHeight="1734"/>
	<SubTexture name="ron death0043" x="2285" y="1683" width="1420" height="472" frameX="-1877" frameY="0" frameWidth="4371" frameHeight="1734"/>
	<SubTexture name="ron death0044" x="2285" y="1683" width="1420" height="472" frameX="-1877" frameY="0" frameWidth="4371" frameHeight="1734"/>
	<SubTexture name="ron death0045" x="3710" y="1683" width="1420" height="472" frameX="-1877" frameY="0" frameWidth="4371" frameHeight="1734"/>
	<SubTexture name="ron death0046" x="3710" y="1683" width="1420" height="472" frameX="-1877" frameY="0" frameWidth="4371" frameHeight="1734"/>
	<SubTexture name="ron death0047" x="3710" y="1683" width="1420" height="472" frameX="-1877" frameY="0" frameWidth="4371" frameHeight="1734"/>
	<SubTexture name="ron death0048" x="3710" y="1683" width="1420" height="472" frameX="-1877" frameY="0" frameWidth="4371" frameHeight="1734"/>
	<SubTexture name="ron death0049" x="3710" y="1683" width="1420" height="472" frameX="-1877" frameY="0" frameWidth="4371" frameHeight="1734"/>
	<SubTexture name="ron death0050" x="3710" y="1683" width="1420" height="472" frameX="-1877" frameY="0" frameWidth="4371" frameHeight="1734"/>
	<SubTexture name="ron death0051" x="3710" y="1683" width="1420" height="472" frameX="-1877" frameY="0" frameWidth="4371" frameHeight="1734"/>
	<SubTexture name="ron death0052" x="3710" y="1683" width="1420" height="472" frameX="-1877" frameY="0" frameWidth="4371" frameHeight="1734"/>
	<SubTexture name="ron death0053" x="3710" y="1683" width="1420" height="472" frameX="-1877" frameY="0" frameWidth="4371" frameHeight="1734"/>
	<SubTexture name="ron death0054" x="3710" y="1683" width="1420" height="472" frameX="-1877" frameY="0" frameWidth="4371" frameHeight="1734"/>
	<SubTexture name="ron death0055" x="2285" y="1683" width="1420" height="472" frameX="-1877" frameY="0" frameWidth="4371" frameHeight="1734"/>
	<SubTexture name="ron death0056" x="2285" y="1683" width="1420" height="472" frameX="-1877" frameY="0" frameWidth="4371" frameHeight="1734"/>
	<SubTexture name="ron death0057" x="5135" y="1683" width="1420" height="472" frameX="-1877" frameY="0" frameWidth="4371" frameHeight="1734"/>
	<SubTexture name="ron death0058" x="6560" y="1683" width="508" height="513" frameX="-1811" frameY="-47" frameWidth="4371" frameHeight="1734"/>
	<SubTexture name="ron death0059" x="6560" y="1683" width="508" height="513" frameX="-1811" frameY="-47" frameWidth="4371" frameHeight="1734"/>
	<SubTexture name="ron death0060" x="6560" y="1683" width="508" height="513" frameX="-1811" frameY="-47" frameWidth="4371" frameHeight="1734"/>
	<SubTexture name="ron death0061" x="6560" y="1683" width="508" height="513" frameX="-1811" frameY="-47" frameWidth="4371" frameHeight="1734"/>
	<SubTexture name="ron death0062" x="6560" y="1683" width="508" height="513" frameX="-1811" frameY="-47" frameWidth="4371" frameHeight="1734"/>
	<SubTexture name="ron death0063" x="7073" y="1683" width="508" height="610" frameX="-1811" frameY="-206" frameWidth="4371" frameHeight="1734"/>
	<SubTexture name="ron death0064" x="7586" y="1683" width="508" height="813" frameX="-1811" frameY="-346" frameWidth="4371" frameHeight="1734"/>
	<SubTexture name="ron death0065" x="5" y="3153" width="508" height="802" frameX="-1811" frameY="-870" frameWidth="4371" frameHeight="1734"/>
	<SubTexture name="ron death0066" x="518" y="3153" width="929" height="249" frameX="-1580" frameY="-1485" frameWidth="4371" frameHeight="1734"/>
	<SubTexture name="ron death0067" x="1452" y="3153" width="238" height="53" frameX="-2032" frameY="-1604" frameWidth="4371" frameHeight="1734"/>
	<SubTexture name="ron death0068" x="1452" y="3153" width="238" height="53" frameX="-2032" frameY="-1604" frameWidth="4371" frameHeight="1734"/>
	<SubTexture name="ron death0069" x="1695" y="3153" width="443" height="53" frameX="-1922" frameY="-1604" frameWidth="4371" frameHeight="1734"/>
	<SubTexture name="ron death0070" x="1695" y="3153" width="443" height="53" frameX="-1922" frameY="-1604" frameWidth="4371" frameHeight="1734"/>
	<SubTexture name="ron death0071" x="2143" y="3153" width="463" height="49" frameX="-1905" frameY="-1604" frameWidth="4371" frameHeight="1734"/>
	<SubTexture name="ron death0072" x="2143" y="3153" width="463" height="49" frameX="-1905" frameY="-1604" frameWidth="4371" frameHeight="1734"/>
	<SubTexture name="ron death0073" x="2611" y="3153" width="471" height="49" frameX="-1901" frameY="-1604" frameWidth="4371" frameHeight="1734"/>
	<SubTexture name="ron death0074" x="2611" y="3153" width="471" height="49" frameX="-1901" frameY="-1604" frameWidth="4371" frameHeight="1734"/>
	<SubTexture name="ron death0075" x="3087" y="3153" width="471" height="49" frameX="-1901" frameY="-1604" frameWidth="4371" frameHeight="1734"/>
	<SubTexture name="ron death0076" x="3087" y="3153" width="471" height="49" frameX="-1901" frameY="-1604" frameWidth="4371" frameHeight="1734"/>
	<SubTexture name="ron death0077" x="3087" y="3153" width="471" height="49" frameX="-1901" frameY="-1604" frameWidth="4371" frameHeight="1734"/>
	<SubTexture name="ron death0078" x="3087" y="3153" width="471" height="49" frameX="-1901" frameY="-1604" frameWidth="4371" frameHeight="1734"/>
	<SubTexture name="ron death0079" x="3087" y="3153" width="471" height="49" frameX="-1901" frameY="-1604" frameWidth="4371" frameHeight="1734"/>
	<SubTexture name="ron death0080" x="3087" y="3153" width="471" height="49" frameX="-1901" frameY="-1604" frameWidth="4371" frameHeight="1734"/>
	<SubTexture name="ron death0081" x="3087" y="3153" width="471" height="49" frameX="-1901" frameY="-1604" frameWidth="4371" frameHeight="1734"/>
	<SubTexture name="ron death0082" x="3087" y="3153" width="471" height="49" frameX="-1901" frameY="-1604" frameWidth="4371" frameHeight="1734"/>
	<SubTexture name="ron death0083" x="3087" y="3153" width="471" height="49" frameX="-1901" frameY="-1604" frameWidth="4371" frameHeight="1734"/>
	<SubTexture name="ron death0084" x="3087" y="3153" width="471" height="49" frameX="-1901" frameY="-1604" frameWidth="4371" frameHeight="1734"/>
	<SubTexture name="ron death0085" x="3087" y="3153" width="471" height="49" frameX="-1901" frameY="-1604" frameWidth="4371" frameHeight="1734"/>
	<SubTexture name="ron death0086" x="3087" y="3153" width="471" height="49" frameX="-1901" frameY="-1604" frameWidth="4371" frameHeight="1734"/>
	<SubTexture name="ron death0087" x="3087" y="3153" width="471" height="49" frameX="-1901" frameY="-1604" frameWidth="4371" frameHeight="1734"/>
	<SubTexture name="ron death0088" x="3087" y="3153" width="471" height="49" frameX="-1901" frameY="-1604" frameWidth="4371" frameHeight="1734"/>
	<SubTexture name="ron death0089" x="3087" y="3153" width="471" height="49" frameX="-1901" frameY="-1604" frameWidth="4371" frameHeight="1734"/>
	<SubTexture name="ron death0090" x="3563" y="3153" width="471" height="116" frameX="-1901" frameY="-1542" frameWidth="4371" frameHeight="1734"/>
	<SubTexture name="ron death0091" x="3563" y="3153" width="471" height="116" frameX="-1901" frameY="-1542" frameWidth="4371" frameHeight="1734"/>
	<SubTexture name="ron death0092" x="4039" y="3153" width="471" height="177" frameX="-1901" frameY="-1476" frameWidth="4371" frameHeight="1734"/>
	<SubTexture name="ron death0093" x="4039" y="3153" width="471" height="177" frameX="-1901" frameY="-1476" frameWidth="4371" frameHeight="1734"/>
	<SubTexture name="ron death0094" x="4515" y="3153" width="471" height="181" frameX="-1901" frameY="-1472" frameWidth="4371" frameHeight="1734"/>
	<SubTexture name="ron death0095" x="4515" y="3153" width="471" height="181" frameX="-1901" frameY="-1472" frameWidth="4371" frameHeight="1734"/>
	<SubTexture name="ron death0096" x="4991" y="3153" width="471" height="182" frameX="-1901" frameY="-1471" frameWidth="4371" frameHeight="1734"/>
	<SubTexture name="ron death0097" x="4991" y="3153" width="471" height="182" frameX="-1901" frameY="-1471" frameWidth="4371" frameHeight="1734"/>
	<SubTexture name="ron retry0000" x="5467" y="3153" width="471" height="183"/>
	<SubTexture name="ron retry0001" x="5467" y="3153" width="471" height="183"/>
	<SubTexture name="ron retry0002" x="5943" y="3153" width="471" height="182" frameX="0" frameY="-1" frameWidth="471" frameHeight="183"/>
	<SubTexture name="ron retry0003" x="5943" y="3153" width="471" height="182" frameX="0" frameY="-1" frameWidth="471" frameHeight="183"/>
	<SubTexture name="ron retry0004" x="6419" y="3153" width="471" height="182" frameX="0" frameY="-1" frameWidth="471" frameHeight="183"/>
	<SubTexture name="ron retry0005" x="6419" y="3153" width="471" height="182" frameX="0" frameY="-1" frameWidth="471" frameHeight="183"/>
	<SubTexture name="ron retry0006" x="6419" y="3153" width="471" height="182" frameX="0" frameY="-1" frameWidth="471" frameHeight="183"/>
	<SubTexture name="ron retry0007" x="6419" y="3153" width="471" height="182" frameX="0" frameY="-1" frameWidth="471" frameHeight="183"/>
	<SubTexture name="ron retry0008" x="6419" y="3153" width="471" height="182" frameX="0" frameY="-1" frameWidth="471" frameHeight="183"/>
	<SubTexture name="ron retry0009" x="6419" y="3153" width="471" height="182" frameX="0" frameY="-1" frameWidth="471" frameHeight="183"/>
	<SubTexture name="ron retry0010" x="6419" y="3153" width="471" height="182" frameX="0" frameY="-1" frameWidth="471" frameHeight="183"/>
	<SubTexture name="ron retry0011" x="6419" y="3153" width="471" height="182" frameX="0" frameY="-1" frameWidth="471" frameHeight="183"/>
	<SubTexture name="ron retry0012" x="6419" y="3153" width="471" height="182" frameX="0" frameY="-1" frameWidth="471" frameHeight="183"/>
	<SubTexture name="ron retry0013" x="6419" y="3153" width="471" height="182" frameX="0" frameY="-1" frameWidth="471" frameHeight="183"/>
	<SubTexture name="ron retry0014" x="6419" y="3153" width="471" height="182" frameX="0" frameY="-1" frameWidth="471" frameHeight="183"/>
</TextureAtlas>
